{
  "sku": "",
  "name": "Andrélon Droogshampoo klei fris & zuiver",
  "brand": "Andrélon",
  "price": "7.49",
  "base_unit_price": "30.57",
  "image_url": "https://images.ctfassets.net/s0lodsnpsezb/381809_M/b2d11af6c1f8ed5e7cd5a35a62b22df6/381809.png",
  "ingredients": "",
  "allergens": "",
  "nutrients_base": {
    "unit": "",
    "value": 0
  },
  "nutrients": [],
  "percentage_alcohol": "",
  "composition": "INGREDIËNTEN: Butane, Isobutane, Propane, Alcohol Denat., Tapioca Starch, Aqua, Isopropyl Myristate, Parfum, Silica, Alpha-Isomethyl Ionone, Benzyl Alcohol, Citronellol, Geraniol, Hexyl Cinnamal, Hydroxycitronellal, Linalool.",
  "extracted_at": "2025-04-25 14:32:26"
}