{
  "sku": "",
  "name": "PLUS Ontbijtverrijker kokossnippers",
  "brand": "PLUS",
  "price": "3.49",
  "base_unit_price": "19.94",
  "image_url": "https://images.ctfassets.net/s0lodsnpsezb/138304_M/8dbfa95121866d14a3d684177b0856bc/138304.png",
  "ingredients": "Kokosnoot",
  "allergens": "",
  "nutrients_base": {
    "unit": "gram",
    "value": 100
  },
  "nutrients": [
    {
      "name": "Energie KJ",
      "value": "2784.0",
      "unit": "kilojoule",
      "parent_code": ""
    },
    {
      "name": "Energie KC",
      "value": "676.0",
      "unit": "KC",
      "parent_code": ""
    },
    {
      "name": "Vet",
      "value": "65.0",
      "unit": "gram",
      "parent_code": ""
    },
    {
      "name": "Waarvan verzadigd vet",
      "value": "49.0",
      "unit": "gram",
      "parent_code": "FAT"
    },
    {
      "name": "Koolhydraten",
      "value": "8.6",
      "unit": "gram",
      "parent_code": ""
    },
    {
      "name": "Waarvan suikers",
      "value": "7.6",
      "unit": "gram",
      "parent_code": "CHOAVL"
    },
    {
      "name": "Eiwitten",
      "value": "7.1",
      "unit": "gram",
      "parent_code": ""
    },
    {
      "name": "Zout",
      "value": "0.07",
      "unit": "gram",
      "parent_code": ""
    }
  ],
  "percentage_alcohol": "",
  "composition": "",
  "extracted_at": "2025-04-25 12:53:24"
}