{
  "sku": "",
  "name": "PLUS Kaiserbroodje volkoren",
  "brand": "PLUS",
  "price": "0.39",
  "base_unit_price": "0.39",
  "image_url": "https://images.ctfassets.net/s0lodsnpsezb/242096_M/8243668d7b2f6c19d52a4a501adebcf0/242096.png",
  "ingredients": "Ingrediënten :67% VOLKORENTARWEMEEL, water, TARWEGLUTEN, bakkersgist, bakkerszout, 0,1% TARWEMOUTMEEL, 0,1% voorverstijfseld VOLKORENTARWEMEEL, meelverbeteraar: ascorbinezuur, 0,01% TARWEKIEMEN.\n\nKan ROGGE, GERST, HAVER en SESAM bevatten.",
  "allergens": "Tarwe, Glutenbevattende granen",
  "nutrients_base": {
    "unit": "gram",
    "value": 100
  },
  "nutrients": [
    {
      "name": "Energie KJ",
      "value": "967.0",
      "unit": "kilojoule",
      "parent_code": ""
    },
    {
      "name": "Energie KC",
      "value": "229.0",
      "unit": "KC",
      "parent_code": ""
    },
    {
      "name": "Vet",
      "value": "1.7",
      "unit": "gram",
      "parent_code": ""
    },
    {
      "name": "Waarvan verzadigd vet",
      "value": "0.3",
      "unit": "gram",
      "parent_code": "FAT"
    },
    {
      "name": "Waarvan enkelvoudig onverzadigd vet",
      "value": "0.2",
      "unit": "gram",
      "parent_code": "FAT"
    },
    {
      "name": "Waarvan meervoudig onverzadigd vet",
      "value": "0.7",
      "unit": "gram",
      "parent_code": "FAT"
    },
    {
      "name": "Koolhydraten",
      "value": "40.6",
      "unit": "gram",
      "parent_code": ""
    },
    {
      "name": "Waarvan suikers",
      "value": "0.5",
      "unit": "gram",
      "parent_code": "CHOAVL"
    },
    {
      "name": "Polyolen",
      "value": "0.0",
      "unit": "gram",
      "parent_code": ""
    },
    {
      "name": "Zetmeel",
      "value": "40.1",
      "unit": "gram",
      "parent_code": ""
    },
    {
      "name": "Vezels",
      "value": "7.0",
      "unit": "gram",
      "parent_code": ""
    },
    {
      "name": "Eiwitten",
      "value": "9.3",
      "unit": "gram",
      "parent_code": ""
    },
    {
      "name": "Zout",
      "value": "1.137",
      "unit": "gram",
      "parent_code": ""
    },
    {
      "name": "Natrium",
      "value": "0.455",
      "unit": "gram",
      "parent_code": ""
    },
    {
      "name": "Trans",
      "value": "0.0",
      "unit": "gram",
      "parent_code": ""
    },
    {
      "name": "Toegevoegde suikers",
      "value": "0.0",
      "unit": "gram",
      "parent_code": ""
    }
  ],
  "percentage_alcohol": "",
  "composition": "",
  "extracted_at": "2025-04-25 13:38:17"
}