{
  "sku": "",
  "name": "innocent Juice tropical",
  "brand": "innocent",
  "price": "3.69",
  "base_unit_price": "4.10",
  "image_url": "https://images.ctfassets.net/s0lodsnpsezb/291223_M/17e4b5c414955ed3a4016e490094e2ea/291223.png",
  "ingredients": "4 geperste appels (51%), 4 ½ geperste sinaasappel (35%), ¼ geperste ananas (12%), een stuk geplette mango (1,7%), een beetje geplette passievrucht (0,8%), wat vitamine c",
  "allergens": "",
  "nutrients_base": {
    "unit": "milliliter",
    "value": 100
  },
  "nutrients": [
    {
      "name": "Energie KJ",
      "value": "184.0",
      "unit": "kilojoule",
      "parent_code": ""
    },
    {
      "name": "Energie KC",
      "value": "43.0",
      "unit": "KC",
      "parent_code": ""
    },
    {
      "name": "Vet",
      "value": "0.01",
      "unit": "gram",
      "parent_code": ""
    },
    {
      "name": "Waarvan verzadigd vet",
      "value": "0.0",
      "unit": "gram",
      "parent_code": "FAT"
    },
    {
      "name": "Koolhydraten",
      "value": "10.0",
      "unit": "gram",
      "parent_code": ""
    },
    {
      "name": "Waarvan suikers",
      "value": "9.5",
      "unit": "gram",
      "parent_code": "CHOAVL"
    },
    {
      "name": "Vezels",
      "value": "0.45",
      "unit": "gram",
      "parent_code": ""
    },
    {
      "name": "Eiwitten",
      "value": "0.38",
      "unit": "gram",
      "parent_code": ""
    },
    {
      "name": "Zout",
      "value": "0.0",
      "unit": "gram",
      "parent_code": ""
    },
    {
      "name": "Vitamine C",
      "value": "25.0",
      "unit": "milligram",
      "parent_code": ""
    }
  ],
  "percentage_alcohol": "0",
  "composition": "",
  "extracted_at": "2025-04-25 13:59:31"
}