{
  "sku": "",
  "name": "Gulpener Franse mosterd",
  "brand": "Gulpener",
  "price": "2.49",
  "base_unit_price": "3.56",
  "image_url": "https://images.ctfassets.net/s0lodsnpsezb/326764_M/03b4b50f93f133b830ca2ccd580490ba/326764.png",
  "ingredients": "Ingrediënten: water, MOSTERDZAAD, natuurazijn, zout, kruiden en specerijen, suiker.",
  "allergens": "Mosterd",
  "nutrients_base": {
    "unit": "gram",
    "value": 100
  },
  "nutrients": [
    {
      "name": "Energie KJ",
      "value": "513.0",
      "unit": "kilojoule",
      "parent_code": ""
    },
    {
      "name": "Energie KC",
      "value": "122.0",
      "unit": "KC",
      "parent_code": ""
    },
    {
      "name": "Vet",
      "value": "6.5",
      "unit": "gram",
      "parent_code": ""
    },
    {
      "name": "Waarvan verzadigd vet",
      "value": "0.4",
      "unit": "gram",
      "parent_code": "FAT"
    },
    {
      "name": "Koolhydraten",
      "value": "6.8",
      "unit": "gram",
      "parent_code": ""
    },
    {
      "name": "Waarvan suikers",
      "value": "1.8",
      "unit": "gram",
      "parent_code": "CHOAVL"
    },
    {
      "name": "Eiwitten",
      "value": "6.4",
      "unit": "gram",
      "parent_code": ""
    },
    {
      "name": "Zout",
      "value": "3.4",
      "unit": "gram",
      "parent_code": ""
    }
  ],
  "percentage_alcohol": "",
  "composition": "",
  "extracted_at": "2025-04-25 14:13:44"
}