{
  "sku": "",
  "name": "Neutraal Cranberries",
  "brand": "Neutraal",
  "price": "2.15",
  "base_unit_price": "8.60",
  "image_url": "https://images.ctfassets.net/s0lodsnpsezb/338931_M/822b06c1f52627a2941d38ee383b6a6a/338931.png",
  "ingredients": "ingrediënten :63% cranberry, 36% rietsuiker, zonnebloemolie.\n\ndit product kan sporen van pinda, noten en sesam bevatten.",
  "allergens": "",
  "nutrients_base": {
    "unit": "gram",
    "value": 100
  },
  "nutrients": [
    {
      "name": "Energie KJ",
      "value": "1397.0",
      "unit": "kilojoule",
      "parent_code": ""
    },
    {
      "name": "Energie KC",
      "value": "329.0",
      "unit": "KC",
      "parent_code": ""
    },
    {
      "name": "Vet",
      "value": "0.41",
      "unit": "gram",
      "parent_code": ""
    },
    {
      "name": "Waarvan verzadigd vet",
      "value": "0.07",
      "unit": "gram",
      "parent_code": "FAT"
    },
    {
      "name": "Waarvan enkelvoudig onverzadigd vet",
      "value": "0.26",
      "unit": "gram",
      "parent_code": "FAT"
    },
    {
      "name": "Waarvan meervoudig onverzadigd vet",
      "value": "0.08",
      "unit": "gram",
      "parent_code": "FAT"
    },
    {
      "name": "Koolhydraten",
      "value": "78.4",
      "unit": "gram",
      "parent_code": ""
    },
    {
      "name": "Waarvan suikers",
      "value": "65.1",
      "unit": "gram",
      "parent_code": "CHOAVL"
    },
    {
      "name": "Polyolen",
      "value": "0.0",
      "unit": "gram",
      "parent_code": ""
    },
    {
      "name": "Zetmeel",
      "value": "13.3",
      "unit": "gram",
      "parent_code": ""
    },
    {
      "name": "Vezels",
      "value": "4.45",
      "unit": "gram",
      "parent_code": ""
    },
    {
      "name": "Eiwitten",
      "value": "0.79",
      "unit": "gram",
      "parent_code": ""
    },
    {
      "name": "Zout",
      "value": "0.01",
      "unit": "gram",
      "parent_code": ""
    },
    {
      "name": "Natrium",
      "value": "0.004",
      "unit": "gram",
      "parent_code": ""
    },
    {
      "name": "Trans",
      "value": "0.0",
      "unit": "gram",
      "parent_code": ""
    },
    {
      "name": "Toegevoegde suikers",
      "value": "36.0",
      "unit": "gram",
      "parent_code": ""
    }
  ],
  "percentage_alcohol": "",
  "composition": "",
  "extracted_at": "2025-04-25 14:17:07"
}