{
  "sku": "",
  "name": "Vergeer jong belegen 48+ stuk",
  "brand": "Vergeer",
  "price": "7.49",
  "base_unit_price": "12.48",
  "image_url": "https://images.ctfassets.net/s0lodsnpsezb/492513_M/b0275089938934089ab682eacfd0a5d1/492513.png",
  "ingredients": "Ingrediënten: gepasteuriseerde KOEMELK, zout, zuursel, microbieel stremsel, kleurstof (carotenen), conserveermiddel (natriumnitraat).",
  "allergens": "Melk",
  "nutrients_base": {
    "unit": "gram",
    "value": 100
  },
  "nutrients": [
    {
      "name": "Energie KJ",
      "value": "1582.0",
      "unit": "kilojoule",
      "parent_code": ""
    },
    {
      "name": "Energie KC",
      "value": "381.0",
      "unit": "KC",
      "parent_code": ""
    },
    {
      "name": "Vet",
      "value": "30.9",
      "unit": "gram",
      "parent_code": ""
    },
    {
      "name": "Waarvan verzadigd vet",
      "value": "18.9",
      "unit": "gram",
      "parent_code": "FAT"
    },
    {
      "name": "Koolhydraten",
      "value": "0.0",
      "unit": "gram",
      "parent_code": ""
    },
    {
      "name": "Waarvan suikers",
      "value": "0.0",
      "unit": "gram",
      "parent_code": "CHOAVL"
    },
    {
      "name": "Eiwitten",
      "value": "25.8",
      "unit": "gram",
      "parent_code": ""
    },
    {
      "name": "Zout",
      "value": "1.96",
      "unit": "gram",
      "parent_code": ""
    }
  ],
  "percentage_alcohol": "",
  "composition": "",
  "extracted_at": "2025-04-25 15:15:33"
}