{
  "sku": "",
  "name": "Pickwick Ginger goodness mint",
  "brand": "Pickwick",
  "price": "2.39",
  "base_unit_price": "0.16",
  "image_url": "https://images.ctfassets.net/s0lodsnpsezb/615026_M/4c78828db14346c13b9e9bbfeb8c9f3c/615026.png",
  "ingredients": "ingrediёnten: gember** (55%), spearmint** (42%), natuurlijk aroma.",
  "allergens": "",
  "nutrients_base": {
    "unit": "milliliter",
    "value": 100
  },
  "nutrients": [
    {
      "name": "Energie KJ",
      "value": "3.4",
      "unit": "kilojoule",
      "parent_code": ""
    },
    {
      "name": "Energie KC",
      "value": "0.8",
      "unit": "KC",
      "parent_code": ""
    },
    {
      "name": "Vet",
      "value": "0.0",
      "unit": "gram",
      "parent_code": ""
    },
    {
      "name": "Waarvan verzadigd vet",
      "value": "0.0",
      "unit": "gram",
      "parent_code": "FAT"
    },
    {
      "name": "Koolhydraten",
      "value": "0.2",
      "unit": "gram",
      "parent_code": ""
    },
    {
      "name": "Waarvan suikers",
      "value": "0.0",
      "unit": "gram",
      "parent_code": "CHOAVL"
    },
    {
      "name": "Eiwitten",
      "value": "0.0",
      "unit": "gram",
      "parent_code": ""
    },
    {
      "name": "Zout",
      "value": "0.0",
      "unit": "gram",
      "parent_code": ""
    }
  ],
  "percentage_alcohol": "",
  "composition": "",
  "extracted_at": "2025-04-25 16:04:47"
}