{
  "sku": "",
  "name": "Tony's Chocolonely Melk romige hazelnoot crunch",
  "brand": "Tony's Chocolonely",
  "price": "4.29",
  "base_unit_price": "23.83",
  "image_url": "https://images.ctfassets.net/s0lodsnpsezb/644992_M/d3009739eadf665d12569467a9d2013b/644992.png",
  "ingredients": "Ingrediënten: suiker, volle MELKpoeder, cacaoboter, cacaomassa, 8% HAZELNOOT, 5% HAZELNOOTpasta, 4% feuilletine koekje (TARWEmeel, suiker, geconcentreerde boter (MELK), lactose (MELK), MELKeiwit, zout, moutextract (GERST), rijsmiddel (natriumwaterstofcarbonaat)), emulgator ((lecithinen (SOJA))). KAN EI EN ANDERE NOTEN BEVATTEN.",
  "allergens": "Tarwe, Gerst en gerstproducten (gluten bevattend graan), Glutenbevattende granen, Soja, Melk, Noten, hazelnoten",
  "nutrients_base": {
    "unit": "gram",
    "value": 100
  },
  "nutrients": [
    {
      "name": "Energie KJ",
      "value": "2334.0",
      "unit": "kilojoule",
      "parent_code": ""
    },
    {
      "name": "Energie KC",
      "value": "559.0",
      "unit": "KC",
      "parent_code": ""
    },
    {
      "name": "Vet",
      "value": "36.0",
      "unit": "gram",
      "parent_code": ""
    },
    {
      "name": "Waarvan verzadigd vet",
      "value": "17.0",
      "unit": "gram",
      "parent_code": "FAT"
    },
    {
      "name": "Koolhydraten",
      "value": "47.0",
      "unit": "gram",
      "parent_code": ""
    },
    {
      "name": "Waarvan suikers",
      "value": "45.0",
      "unit": "gram",
      "parent_code": "CHOAVL"
    },
    {
      "name": "Eiwitten",
      "value": "8.4",
      "unit": "gram",
      "parent_code": ""
    },
    {
      "name": "Zout",
      "value": "0.23",
      "unit": "gram",
      "parent_code": ""
    }
  ],
  "percentage_alcohol": "",
  "composition": "",
  "extracted_at": "2025-04-25 16:11:20"
}