{
  "sku": "",
  "name": "Bronchostop Hoestdrank",
  "brand": "Bronchostop",
  "price": "13.49",
  "base_unit_price": "112.42",
  "image_url": "https://images.ctfassets.net/s0lodsnpsezb/726288_M/0f65ce30ec91dda8d47254aff3e6d2c5/726288.png",
  "ingredients": "Hulpstoffen: \no.a. methyl-4-hydroxybenzoaat, propyl-4-hydroxybenzoaat.",
  "allergens": "",
  "nutrients_base": {
    "unit": "",
    "value": 0
  },
  "nutrients": [],
  "percentage_alcohol": "",
  "composition": "Ingrediënten:\n15 ml (=16,7 g) bevat: \n120 mg droog extract van de gedroogde bovengrondse delen van de bloeiende Thymus vulgaris L. en/of Thymus zygis L., overeenkomend met 840-1560 mg gedroogd tijmkruid.  \n830 mg vloeibaar extract van de gepelde, gedroogde wortel van de Althaea officinalis L., overeenkomend met 59-69 mg gedroogde heemstwortel.",
  "extracted_at": "2025-04-25 16:31:51"
}