{
  "sku": "",
  "name": "Otrivin Spray 0.05%",
  "brand": "Otrivin",
  "price": "6.79",
  "base_unit_price": "679.00",
  "image_url": "https://images.ctfassets.net/s0lodsnpsezb/866169_M/9a5b87edd3a918ef771cf184ba77c95a/866169.png",
  "ingredients": "Bevat : \ndinatriumedetaat, benzalkoniumchloride, dinatriumfosfaat dodecahydraat, natiumwaterstoffosfaat monohydraat, natriumchloride, sorbitol, methylhydroxypropylcellulose 4000 mPa.s en gezuiverd water..",
  "allergens": "",
  "nutrients_base": {
    "unit": "",
    "value": 0
  },
  "nutrients": [],
  "percentage_alcohol": "",
  "composition": "Zie bijsluiter",
  "extracted_at": "2025-04-25 16:57:41"
}