{
  "sku": "",
  "name": "Almhof Roomyoghurt morello kers",
  "brand": "Almhof",
  "price": "1.39",
  "base_unit_price": "9.27",
  "image_url": "https://images.ctfassets.net/s0lodsnpsezb/870449_M/fbb463389276430223fc4e806c0cc860/870449.png",
  "ingredients": "Ingredienten:\nROOMYOGHURT, suiker, 6,1% kersen, 2,9% kersensap uit concentraat, maïszetmeel, gedroogd WEI-product, plantenconcentraten (wortel, druif), natuurlijk aroma.",
  "allergens": "Melk",
  "nutrients_base": {
    "unit": "gram",
    "value": 100
  },
  "nutrients": [
    {
      "name": "Energie KJ",
      "value": "576.0",
      "unit": "kilojoule",
      "parent_code": ""
    },
    {
      "name": "Energie KC",
      "value": "138.0",
      "unit": "KC",
      "parent_code": ""
    },
    {
      "name": "Vet",
      "value": "8.1",
      "unit": "gram",
      "parent_code": ""
    },
    {
      "name": "Waarvan verzadigd vet",
      "value": "5.4",
      "unit": "gram",
      "parent_code": "FAT"
    },
    {
      "name": "Koolhydraten",
      "value": "12.7",
      "unit": "gram",
      "parent_code": ""
    },
    {
      "name": "Waarvan suikers",
      "value": "11.8",
      "unit": "gram",
      "parent_code": "CHOAVL"
    },
    {
      "name": "Eiwitten",
      "value": "2.7",
      "unit": "gram",
      "parent_code": ""
    },
    {
      "name": "Zout",
      "value": "0.09",
      "unit": "gram",
      "parent_code": ""
    }
  ],
  "percentage_alcohol": "",
  "composition": "",
  "extracted_at": "2025-04-25 16:58:02"
}