{
  "sku": "",
  "name": "Amstel Radler citroen 0.0 bier fles",
  "brand": "Amstel",
  "price": "0.97",
  "base_unit_price": "3.23",
  "image_url": "https://images.ctfassets.net/s0lodsnpsezb/146688_M/1dc8412d1f4c3c4d61f33cc42a36a590/146688.png",
  "ingredients": "Ingrediënten: koolzuurhoudend water, GERSTEMOUT, suiker, vruchtensap uit concentraat (citroensap 2,7%, sinaasappelsap, limoensap, acerolasap), hop, hopextract, natuurlijke aroma's, geconcentreerd citroenextract, stabilisator: johannesbroodpitmeel.",
  "allergens": "Gerst en gerstproducten (gluten bevattend graan), Glutenbevattende granen",
  "nutrients_base": {
    "unit": "milliliter",
    "value": 100
  },
  "nutrients": [
    {
      "name": "Energie KJ",
      "value": "118.0",
      "unit": "kilojoule",
      "parent_code": ""
    },
    {
      "name": "Energie KC",
      "value": "28.0",
      "unit": "KC",
      "parent_code": ""
    },
    {
      "name": "Vet",
      "value": "0.1",
      "unit": "gram",
      "parent_code": ""
    },
    {
      "name": "Waarvan verzadigd vet",
      "value": "0.0",
      "unit": "gram",
      "parent_code": "FAT"
    },
    {
      "name": "Koolhydraten",
      "value": "6.9",
      "unit": "gram",
      "parent_code": ""
    },
    {
      "name": "Waarvan suikers",
      "value": "5.6",
      "unit": "gram",
      "parent_code": "CHOAVL"
    },
    {
      "name": "Eiwitten",
      "value": "0.1",
      "unit": "gram",
      "parent_code": ""
    },
    {
      "name": "Zout",
      "value": "0.01",
      "unit": "gram",
      "parent_code": ""
    }
  ],
  "percentage_alcohol": "0",
  "composition": "",
  "extracted_at": "2025-04-25 12:55:51"
}