{
  "sku": "",
  "name": "Uit de keuken van Grill & Gaar Gehaktballetjes ketjap",
  "brand": "Uit de keuken van",
  "price": "15.99",
  "base_unit_price": "15.99",
  "image_url": "https://images.ctfassets.net/s0lodsnpsezb/332814_M/9299fb3910490ad7423caa92354b8951/332814.png",
  "ingredients": "Gehaktballetjes (varkensvlees, rundvlees, scharrelei, TARWEBLOEM, voedingszuur: e326/e262/e330, zout, specerijen, tarwezemelen, dextrose, conserveermiddel: e202, zonnebloemolie, gebrande suiker), saus met ketjapsmaak (water, suiker, suikerstroop, gemodificeerd aardappelzetmeel, azijn, gekarameliseerde suiker, zout, specerijen (knoflookpoeder, uipoeder, gemberpoeder), natuurlijk aroma, conserveermiddel: e202).\n\nvegetarisch? nee.\nveganistisch? nee.",
  "allergens": "Tarwe",
  "nutrients_base": {
    "unit": "gram",
    "value": 100
  },
  "nutrients": [],
  "percentage_alcohol": "",
  "composition": "",
  "extracted_at": "2025-04-25 14:15:30"
}