{
  "sku": "",
  "name": "Biologisch PLUS Bio boterhamworst",
  "brand": "Biologisch PLUS",
  "price": "2.15",
  "base_unit_price": "21.54",
  "image_url": "https://images.ctfassets.net/s0lodsnpsezb/427531_M/e80b557a5d7524245478835410112e93/427531.png",
  "ingredients": "ingrediënten :62% varkensvlees*, water, 10% rundvlees*, varkensspek*, aardappelzetmeel*, voedingszuur: e325/e330, conserveermiddel: e267*/ e250, zout, specerijen*, antioxidant: e301.\n\n* van biologische oorsprong",
  "allergens": "",
  "nutrients_base": {
    "unit": "gram",
    "value": 100
  },
  "nutrients": [
    {
      "name": "Energie KJ",
      "value": "1233.0",
      "unit": "kilojoule",
      "parent_code": ""
    },
    {
      "name": "Energie KC",
      "value": "298.0",
      "unit": "KC",
      "parent_code": ""
    },
    {
      "name": "Vet",
      "value": "26.47",
      "unit": "gram",
      "parent_code": ""
    },
    {
      "name": "Waarvan verzadigd vet",
      "value": "10.0",
      "unit": "gram",
      "parent_code": "FAT"
    },
    {
      "name": "Waarvan enkelvoudig onverzadigd vet",
      "value": "13.65",
      "unit": "gram",
      "parent_code": "FAT"
    },
    {
      "name": "Waarvan meervoudig onverzadigd vet",
      "value": "2.8",
      "unit": "gram",
      "parent_code": "FAT"
    },
    {
      "name": "Koolhydraten",
      "value": "3.41",
      "unit": "gram",
      "parent_code": ""
    },
    {
      "name": "Waarvan suikers",
      "value": "0.17",
      "unit": "gram",
      "parent_code": "CHOAVL"
    },
    {
      "name": "Polyolen",
      "value": "0.0",
      "unit": "gram",
      "parent_code": ""
    },
    {
      "name": "Zetmeel",
      "value": "3.24",
      "unit": "gram",
      "parent_code": ""
    },
    {
      "name": "Vezels",
      "value": "0.1",
      "unit": "gram",
      "parent_code": ""
    },
    {
      "name": "Eiwitten",
      "value": "11.48",
      "unit": "gram",
      "parent_code": ""
    },
    {
      "name": "Zout",
      "value": "1.74",
      "unit": "gram",
      "parent_code": ""
    },
    {
      "name": "Natrium",
      "value": "0.696",
      "unit": "gram",
      "parent_code": ""
    },
    {
      "name": "Trans",
      "value": "0.02",
      "unit": "gram",
      "parent_code": ""
    },
    {
      "name": "Toegevoegde suikers",
      "value": "0.0",
      "unit": "gram",
      "parent_code": ""
    }
  ],
  "percentage_alcohol": "",
  "composition": "",
  "extracted_at": "2025-04-25 14:49:13"
}