{
  "sku": "",
  "name": "Baktat Gedroogde tomaten in olie",
  "brand": "Baktat",
  "price": "3.09",
  "base_unit_price": "9.97",
  "image_url": "https://images.ctfassets.net/s0lodsnpsezb/436948_M/07c5cd1c0f8657eb246ed4092549e095/436948.png",
  "ingredients": "tomaten (60%), koolzaadolie, zout, knoflook, jeneverbes, laurierblad, kruiden.",
  "allergens": "",
  "nutrients_base": {
    "unit": "gram",
    "value": 100
  },
  "nutrients": [
    {
      "name": "Energie KJ",
      "value": "1550.0",
      "unit": "kilojoule",
      "parent_code": ""
    },
    {
      "name": "Energie KC",
      "value": "376.0",
      "unit": "KC",
      "parent_code": ""
    },
    {
      "name": "Vet",
      "value": "37.0",
      "unit": "gram",
      "parent_code": ""
    },
    {
      "name": "Waarvan verzadigd vet",
      "value": "3.0",
      "unit": "gram",
      "parent_code": "FAT"
    },
    {
      "name": "Koolhydraten",
      "value": "4.7",
      "unit": "gram",
      "parent_code": ""
    },
    {
      "name": "Waarvan suikers",
      "value": "3.0",
      "unit": "gram",
      "parent_code": "CHOAVL"
    },
    {
      "name": "Eiwitten",
      "value": "2.1",
      "unit": "gram",
      "parent_code": ""
    },
    {
      "name": "Zout",
      "value": "1.8",
      "unit": "gram",
      "parent_code": ""
    }
  ],
  "percentage_alcohol": "",
  "composition": "",
  "extracted_at": "2025-04-25 14:53:49"
}