{
  "sku": "",
  "name": "Venco Topdrop 4 rollen",
  "brand": "Venco",
  "price": "1.99",
  "base_unit_price": "10.59",
  "image_url": "https://images.ctfassets.net/s0lodsnpsezb/456625_M/624cc5486293a97443eee56e79d9e595/456625.png",
  "ingredients": "Ingrediënten: Suiker, gemodificeerd zetmeel, glucosestroop, zetmeel, gelatine, salmiakzout, melado, zoethoutwortelextract, plantaardige oliën (kokos, palm), natuurlijk aroma, glansmiddel (bijenwas), TARWEBLOEM",
  "allergens": "Tarwe, Glutenbevattende granen",
  "nutrients_base": {
    "unit": "gram",
    "value": 100
  },
  "nutrients": [
    {
      "name": "Energie KJ",
      "value": "1430.0",
      "unit": "kilojoule",
      "parent_code": ""
    },
    {
      "name": "Energie KC",
      "value": "337.0",
      "unit": "KC",
      "parent_code": ""
    },
    {
      "name": "Vet",
      "value": "0.2",
      "unit": "gram",
      "parent_code": ""
    },
    {
      "name": "Waarvan verzadigd vet",
      "value": "0.2",
      "unit": "gram",
      "parent_code": "FAT"
    },
    {
      "name": "Koolhydraten",
      "value": "79.0",
      "unit": "gram",
      "parent_code": ""
    },
    {
      "name": "Waarvan suikers",
      "value": "44.0",
      "unit": "gram",
      "parent_code": "CHOAVL"
    },
    {
      "name": "Eiwitten",
      "value": "4.7",
      "unit": "gram",
      "parent_code": ""
    },
    {
      "name": "Zout",
      "value": "0.07",
      "unit": "gram",
      "parent_code": ""
    }
  ],
  "percentage_alcohol": "",
  "composition": "",
  "extracted_at": "2025-04-25 15:02:01"
}