{
  "sku": "",
  "name": "Silvo Viskruiden",
  "brand": "Silvo",
  "price": "2.99",
  "base_unit_price": "54.36",
  "image_url": "https://images.ctfassets.net/s0lodsnpsezb/595414_M/c71479d2d999f3ed94154e9e342a3971/595414.png",
  "ingredients": "Ingrediënten: Specerijen 32,7% (gedroogde ui, dillezaad 3%, zwarte peper), zeezout 19%, suiker, kruiden 9% (perselie, dilleblad 4%), aroma (bevat TARWE, GERST), citroensapconcentraat, gedroogde citroenschil, gedroogde sinaasappelschil, voedingszuur: citroenzuur, zonnebloemolie, anti-klontermiddel: siliciumdioxide, Totale gehalte aan kruiden en specerijen: 41,7%.",
  "allergens": "Tarwe, Gerst en gerstproducten (gluten bevattend graan), Glutenbevattende granen",
  "nutrients_base": {
    "unit": "gram",
    "value": 100
  },
  "nutrients": [
    {
      "name": "Energie KJ",
      "value": "1053.0",
      "unit": "kilojoule",
      "parent_code": ""
    },
    {
      "name": "Energie KC",
      "value": "249.0",
      "unit": "KC",
      "parent_code": ""
    },
    {
      "name": "Vet",
      "value": "2.4",
      "unit": "gram",
      "parent_code": ""
    },
    {
      "name": "Waarvan verzadigd vet",
      "value": "0.3",
      "unit": "gram",
      "parent_code": "FAT"
    },
    {
      "name": "Koolhydraten",
      "value": "46.2",
      "unit": "gram",
      "parent_code": ""
    },
    {
      "name": "Waarvan suikers",
      "value": "25.8",
      "unit": "gram",
      "parent_code": "CHOAVL"
    },
    {
      "name": "Eiwitten",
      "value": "6.7",
      "unit": "gram",
      "parent_code": ""
    },
    {
      "name": "Zout",
      "value": "22.02",
      "unit": "gram",
      "parent_code": ""
    }
  ],
  "percentage_alcohol": "",
  "composition": "",
  "extracted_at": "2025-04-25 15:56:26"
}