{
  "sku": "",
  "name": "Kuhne Paprika salade",
  "brand": "Kuhne",
  "price": "1.89",
  "base_unit_price": "5.11",
  "image_url": "https://images.ctfassets.net/s0lodsnpsezb/612270_M/6b520d0966753608f7dcb3be08b9e6eb/612270.png",
  "ingredients": "Ingrediënten: rode paprika, natuurazijn, suiker, zout.",
  "allergens": "",
  "nutrients_base": {
    "unit": "gram",
    "value": 100
  },
  "nutrients": [
    {
      "name": "Energie KJ",
      "value": "144.0",
      "unit": "kilojoule",
      "parent_code": ""
    },
    {
      "name": "Energie KC",
      "value": "33.0",
      "unit": "KC",
      "parent_code": ""
    },
    {
      "name": "Vet",
      "value": "0.2",
      "unit": "gram",
      "parent_code": ""
    },
    {
      "name": "Waarvan verzadigd vet",
      "value": "0.1",
      "unit": "gram",
      "parent_code": "FAT"
    },
    {
      "name": "Koolhydraten",
      "value": "5.5",
      "unit": "gram",
      "parent_code": ""
    },
    {
      "name": "Waarvan suikers",
      "value": "5.0",
      "unit": "gram",
      "parent_code": "CHOAVL"
    },
    {
      "name": "Vezels",
      "value": "2.1",
      "unit": "gram",
      "parent_code": ""
    },
    {
      "name": "Eiwitten",
      "value": "1.0",
      "unit": "gram",
      "parent_code": ""
    },
    {
      "name": "Zout",
      "value": "1.0",
      "unit": "gram",
      "parent_code": ""
    }
  ],
  "percentage_alcohol": "",
  "composition": "",
  "extracted_at": "2025-04-25 16:03:54"
}