{
  "sku": "",
  "name": "Nestlé 6+ Yogolino toetje banaan",
  "brand": "Nestlé",
  "price": "3.25",
  "base_unit_price": "8.13",
  "image_url": "https://images.ctfassets.net/s0lodsnpsezb/826436_M/8fee7617064d0023e01591f666a59d2b/826436.png",
  "ingredients": "Ingrediënten: volle MELK 71.1%. water. suiker. bananenpuree 5%. zetmeel. suiker. verdikkingsmiddel (pectine). geconcentreerd citroensap. MELKfermenten (MELK). aroma. ",
  "allergens": "Melk, Lactose",
  "nutrients_base": {
    "unit": "gram",
    "value": 100
  },
  "nutrients": [
    {
      "name": "Energie KJ",
      "value": "239.0",
      "unit": "kilojoule",
      "parent_code": ""
    },
    {
      "name": "Energie KC",
      "value": "78.0",
      "unit": "KC",
      "parent_code": ""
    },
    {
      "name": "Vet",
      "value": "2.3",
      "unit": "gram",
      "parent_code": ""
    },
    {
      "name": "Waarvan verzadigd vet",
      "value": "1.5",
      "unit": "gram",
      "parent_code": "FAT"
    },
    {
      "name": "Koolhydraten",
      "value": "12.0",
      "unit": "gram",
      "parent_code": ""
    },
    {
      "name": "Waarvan suikers",
      "value": "6.3",
      "unit": "gram",
      "parent_code": "CHOAVL"
    },
    {
      "name": "Vezels",
      "value": "0.5",
      "unit": "gram",
      "parent_code": ""
    },
    {
      "name": "Eiwitten",
      "value": "2.5",
      "unit": "gram",
      "parent_code": ""
    },
    {
      "name": "Zout",
      "value": "0.07",
      "unit": "gram",
      "parent_code": ""
    },
    {
      "name": "Calcium",
      "value": "85.0",
      "unit": "milligram",
      "parent_code": ""
    }
  ],
  "percentage_alcohol": "",
  "composition": "",
  "extracted_at": "2025-04-25 16:52:47"
}