{
  "sku": "",
  "name": "Remia American Fritessaus Topdown",
  "brand": "Remia",
  "price": "1.99",
  "base_unit_price": "3.98",
  "image_url": "https://images.ctfassets.net/s0lodsnpsezb/870593_M/7d866e025e0386445b86f030de1253f4/870593.png",
  "ingredients": "Ingrediënten: water, raapolie, natuuazijn, gemodificeerd maiszetmeel, suiker, peterselie 2,8%, MOSTERD (water, MOSTERDZADEN, natuurazijn, specerijen), vrije uitloop EIGEEL1, zout, verdikkingsmiddel: guarpitmeel, voedingszuur: melkzuur, knoflook, conserveermiddel: kaliumsorbaat, kleurstof: riboflavine, natuurlijk aroma, specerijen, prei-extract, antioxidant: E385, zoetstof: sucralose.  1=Beter Levenkeurmerk 2 sterren.",
  "allergens": "Ei, Mosterd",
  "nutrients_base": {
    "unit": "milliliter",
    "value": 100
  },
  "nutrients": [
    {
      "name": "Energie KJ",
      "value": "873.0",
      "unit": "kilojoule",
      "parent_code": ""
    },
    {
      "name": "Energie KC",
      "value": "211.0",
      "unit": "KC",
      "parent_code": ""
    },
    {
      "name": "Vet",
      "value": "19.0",
      "unit": "gram",
      "parent_code": ""
    },
    {
      "name": "Waarvan verzadigd vet",
      "value": "1.5",
      "unit": "gram",
      "parent_code": "FAT"
    },
    {
      "name": "Koolhydraten",
      "value": "8.3",
      "unit": "gram",
      "parent_code": ""
    },
    {
      "name": "Waarvan suikers",
      "value": "3.4",
      "unit": "gram",
      "parent_code": "CHOAVL"
    },
    {
      "name": "Eiwitten",
      "value": "0.6",
      "unit": "gram",
      "parent_code": ""
    },
    {
      "name": "Zout",
      "value": "1.6",
      "unit": "gram",
      "parent_code": ""
    }
  ],
  "percentage_alcohol": "",
  "composition": "",
  "extracted_at": "2025-04-25 16:58:03"
}