{
  "sku": "",
  "name": "La Morena Jalapeno slices",
  "brand": "La Morena",
  "price": "3.39",
  "base_unit_price": "14.74",
  "image_url": "https://images.ctfassets.net/s0lodsnpsezb/908244_M/20861241ae4b71ea51cf3387313e3002/908244.png",
  "ingredients": "jalapeño peper, water, bakkerszout, azijn, specerijen, verstevigingsmiddel: calciumchloride.",
  "allergens": "",
  "nutrients_base": {
    "unit": "gram",
    "value": 100
  },
  "nutrients": [
    {
      "name": "Energie KJ",
      "value": "69.0",
      "unit": "kilojoule",
      "parent_code": ""
    },
    {
      "name": "Energie KC",
      "value": "17.0",
      "unit": "KC",
      "parent_code": ""
    },
    {
      "name": "Vet",
      "value": "0.2",
      "unit": "gram",
      "parent_code": ""
    },
    {
      "name": "Waarvan verzadigd vet",
      "value": "0.0",
      "unit": "gram",
      "parent_code": "FAT"
    },
    {
      "name": "Koolhydraten",
      "value": "1.8",
      "unit": "gram",
      "parent_code": ""
    },
    {
      "name": "Waarvan suikers",
      "value": "0.0",
      "unit": "gram",
      "parent_code": "CHOAVL"
    },
    {
      "name": "Eiwitten",
      "value": "0.5",
      "unit": "gram",
      "parent_code": ""
    },
    {
      "name": "Zout",
      "value": "3.2",
      "unit": "gram",
      "parent_code": ""
    }
  ],
  "percentage_alcohol": "",
  "composition": "",
  "extracted_at": "2025-04-25 17:04:52"
}