{
  "sku": "",
  "name": "PLUS Boerentrots Haaskarbonade 2 stuks",
  "brand": "PLUS Boerentrots",
  "price": "3.84",
  "base_unit_price": "11.29",
  "image_url": "https://images.ctfassets.net/s0lodsnpsezb/993889_M/020bf78f3f64365c517a7dc837b4af88/993889.png",
  "ingredients": "ingrediënten :varkensvlees*.\n*beter leven keurmerk 1 ster",
  "allergens": "",
  "nutrients_base": {
    "unit": "gram",
    "value": 100
  },
  "nutrients": [
    {
      "name": "Energie KJ",
      "value": "632.0",
      "unit": "kilojoule",
      "parent_code": ""
    },
    {
      "name": "Energie KC",
      "value": "151.0",
      "unit": "KC",
      "parent_code": ""
    },
    {
      "name": "Vet",
      "value": "6.7",
      "unit": "gram",
      "parent_code": ""
    },
    {
      "name": "Waarvan verzadigd vet",
      "value": "2.6",
      "unit": "gram",
      "parent_code": "FAT"
    },
    {
      "name": "Waarvan enkelvoudig onverzadigd vet",
      "value": "2.7",
      "unit": "gram",
      "parent_code": "FAT"
    },
    {
      "name": "Waarvan meervoudig onverzadigd vet",
      "value": "0.9",
      "unit": "gram",
      "parent_code": "FAT"
    },
    {
      "name": "Koolhydraten",
      "value": "0.0",
      "unit": "gram",
      "parent_code": ""
    },
    {
      "name": "Waarvan suikers",
      "value": "0.0",
      "unit": "gram",
      "parent_code": "CHOAVL"
    },
    {
      "name": "Polyolen",
      "value": "0.0",
      "unit": "gram",
      "parent_code": ""
    },
    {
      "name": "Zetmeel",
      "value": "0.0",
      "unit": "gram",
      "parent_code": ""
    },
    {
      "name": "Vezels",
      "value": "0.0",
      "unit": "gram",
      "parent_code": ""
    },
    {
      "name": "Eiwitten",
      "value": "22.6",
      "unit": "gram",
      "parent_code": ""
    },
    {
      "name": "Zout",
      "value": "0.153",
      "unit": "gram",
      "parent_code": ""
    },
    {
      "name": "Natrium",
      "value": "0.061",
      "unit": "gram",
      "parent_code": ""
    },
    {
      "name": "Trans",
      "value": "0.0",
      "unit": "gram",
      "parent_code": ""
    },
    {
      "name": "Toegevoegde suikers",
      "value": "0.0",
      "unit": "gram",
      "parent_code": ""
    }
  ],
  "percentage_alcohol": "",
  "composition": "",
  "extracted_at": "2025-04-25 17:27:02"
}